telegram_message/__init__.py
telegram_message/telegram_message.py
telegram_message-0.2.0.dist-info/METADATA
telegram_message-0.2.0.dist-info/WHEEL
telegram_message-0.2.0.dist-info/top_level.txt
telegram_message-0.2.0.dist-info/RECORD
