Metadata-Version: 2.1
Name: telegram_message
Version: 0.2.0
Summary: sending notifications to telegram
Author: Tetiana
Author-email: tetyana.d@nitra.dev
